petrone/__init__.py
petrone/crc.py
petrone/drone.py
petrone/protocol.py
petrone/receiver.py
petrone/storage.py
petrone/system.py
petrone-0.1.58.dist-info/LICENSE
petrone-0.1.58.dist-info/METADATA
petrone-0.1.58.dist-info/WHEEL
petrone-0.1.58.dist-info/top_level.txt
petrone-0.1.58.dist-info/RECORD
