Metadata-Version: 2.1
Name: petrone
Version: 0.1.58
Summary: Library for BYROBOT PETRONE
Home-page: http://www.byrobot.co.kr
Author: BYROBOT
Author-email: dev@byrobot.co.kr
License: UNKNOWN
Platform: UNKNOWN
Requires-Dist: pyserial (>=3.4)
Requires-Dist: numpy (>=1.15.4)
Requires-Dist: colorama (>=0.4.0)
